<?xml version="1.0" encoding="UTF-8" standalone="yes"?>
<ProxyEndpoint name="default">
    <Description/>
    <Flows>
        <Flow name="all">
            <Description/>
            <Request/>
            <Response>
            </Response>
            <Condition>(proxy.pathsuffix MatchesPath &quot;/apigee/**&quot;) and (request.verb = &quot;GET&quot;)</Condition>
        </Flow>
        <Flow name="forecastweather_node">
            <Description/>
            <Request/>
            <Response>
            </Response>
            <Condition>(proxy.pathsuffix MatchesPath &quot;/forecastweather_node/**&quot;) and (request.verb = &quot;GET&quot;)</Condition>
        </Flow>
        <Flow name="node">
            <Description/>
            <Request/>
            <Response>
            </Response>
            <Condition>(proxy.pathsuffix MatchesPath &quot;/images/**&quot;) and (request.verb = &quot;GET&quot;)</Condition>
        </Flow>
        <Flow name="SimpleJavaCallout">
            <Description/>
            <Request/>
            <Response>
        <!-- Disabled by default - JavaCallout -->
        <!--    <Step>
                    <FaultRules/>
                    <Name>SimpleJavaCallout</Name>
                </Step> -->
            </Response>
            <Condition>(proxy.pathsuffix MatchesPath &quot;/javacallout&quot;) and (request.verb = &quot;GET&quot;)</Condition>
        </Flow>
    </Flows>
    <PreFlow name="PreFlow">
        <Request/>
        <Response/>
    </PreFlow>
    <HTTPProxyConnection>
        <BasePath>/node-basic-auth</BasePath>
        <VirtualHost>default</VirtualHost>
        <VirtualHost>secure</VirtualHost>
    </HTTPProxyConnection>
    <RouteRule name="default">
        <Condition>(proxy.pathsuffix MatchesPath &quot;/apigee/**&quot;) and (request.verb = &quot;GET&quot;)</Condition>
        <TargetEndpoint>default</TargetEndpoint>
    </RouteRule>
    <!-- <RouteRule name="NoRoute"></RouteRule> -->
    <RouteRule name="node">
        <TargetEndpoint>node</TargetEndpoint>
    </RouteRule>
    <PostFlow name="PostFlow">
        <Request/>
        <Response/>
    </PostFlow>
</ProxyEndpoint>
